setup.py
jpnfmt/__init__.py
jpnfmt/__version__.py
jpnfmt/jpnfmt.py
jpnfmt.egg-info/PKG-INFO
jpnfmt.egg-info/SOURCES.txt
jpnfmt.egg-info/dependency_links.txt
jpnfmt.egg-info/requires.txt
jpnfmt.egg-info/top_level.txt