Metadata-Version: 2.1
Name: jpnfmt
Version: 0.0.0
Summary: 日本語整形モジュール
Home-page: https://github.com/lotcarnage/jpnfmt
Author: lotcarnage
Author-email: lotcarnage@gmail.com
License: MIT
Platform: UNKNOWN
Requires-Python: >=3.8
